LICENSE.txt
MANIFEST.in
README.rst
setup.cfg
setup.py
lona_bootstrap_5/__init__.py
lona_bootstrap_5/messages.py
lona_bootstrap_5/modal.py
lona_bootstrap_5/nodes.py
lona_bootstrap_5/progress.py
lona_bootstrap_5/static_files.py
lona_bootstrap_5/switch.py
lona_bootstrap_5/templating.py
lona_bootstrap_5.egg-info/PKG-INFO
lona_bootstrap_5.egg-info/SOURCES.txt
lona_bootstrap_5.egg-info/dependency_links.txt
lona_bootstrap_5.egg-info/top_level.txt
lona_bootstrap_5/static/bootstrap5-widgets.js
lona_bootstrap_5/static/bootstrap-5.1.0-dist/css/bootstrap-grid.css
lona_bootstrap_5/static/bootstrap-5.1.0-dist/css/bootstrap-grid.css.map
lona_bootstrap_5/static/bootstrap-5.1.0-dist/css/bootstrap-grid.min.css
lona_bootstrap_5/static/bootstrap-5.1.0-dist/css/bootstrap-grid.min.css.map
lona_bootstrap_5/static/bootstrap-5.1.0-dist/css/bootstrap-grid.rtl.css
lona_bootstrap_5/static/bootstrap-5.1.0-dist/css/bootstrap-grid.rtl.css.map
lona_bootstrap_5/static/bootstrap-5.1.0-dist/css/bootstrap-grid.rtl.min.css
lona_bootstrap_5/static/bootstrap-5.1.0-dist/css/bootstrap-grid.rtl.min.css.map
lona_bootstrap_5/static/bootstrap-5.1.0-dist/css/bootstrap-reboot.css
lona_bootstrap_5/static/bootstrap-5.1.0-dist/css/bootstrap-reboot.css.map
lona_bootstrap_5/static/bootstrap-5.1.0-dist/css/bootstrap-reboot.min.css
lona_bootstrap_5/static/bootstrap-5.1.0-dist/css/bootstrap-reboot.min.css.map
lona_bootstrap_5/static/bootstrap-5.1.0-dist/css/bootstrap-reboot.rtl.css
lona_bootstrap_5/static/bootstrap-5.1.0-dist/css/bootstrap-reboot.rtl.css.map
lona_bootstrap_5/static/bootstrap-5.1.0-dist/css/bootstrap-reboot.rtl.min.css
lona_bootstrap_5/static/bootstrap-5.1.0-dist/css/bootstrap-reboot.rtl.min.css.map
lona_bootstrap_5/static/bootstrap-5.1.0-dist/css/bootstrap-utilities.css
lona_bootstrap_5/static/bootstrap-5.1.0-dist/css/bootstrap-utilities.css.map
lona_bootstrap_5/static/bootstrap-5.1.0-dist/css/bootstrap-utilities.min.css
lona_bootstrap_5/static/bootstrap-5.1.0-dist/css/bootstrap-utilities.min.css.map
lona_bootstrap_5/static/bootstrap-5.1.0-dist/css/bootstrap-utilities.rtl.css
lona_bootstrap_5/static/bootstrap-5.1.0-dist/css/bootstrap-utilities.rtl.css.map
