Metadata-Version: 1.1
Name: lona-bootstrap-5
Version: 0.3
Summary: Bootstrap 5 widgets for Lona
Home-page: https://github.com/lona-web-org/lona-bootstrap-5
Author: Florian Scherf
Author-email: mail@florianscherf.de
License: MIT
Platform: UNKNOWN
Classifier: License :: OSI Approved :: MIT License
